bbprep/__init__.py
bbprep/_version.py
bbprep/generators.py
bbprep/selectors.py
bbprep/_internal/__init__.py
bbprep/_internal/ensemble/__init__.py
bbprep/_internal/ensemble/calculators.py
bbprep/_internal/ensemble/ensemble.py
bbprep/_internal/generators/__init__.py
bbprep/_internal/generators/etkdg.py
bbprep/_internal/generators/generator.py
bbprep/_internal/generators/geometry_scanner.py
bbprep/_internal/generators/scanner_by_selector.py
bbprep/_internal/generators/targets.py
bbprep/_internal/generators/torsion_scanner.py
bbprep/_internal/generators/utilities.py
bbprep/_internal/modifiers/__init__.py
bbprep/_internal/modifiers/distanced_functional_groups.py
bbprep/_internal/modifiers/modifier.py
bbprep/_internal/modifiers/random_functional_groups.py
bbprep/_internal/modifiers/reorient_panel.py
bbprep/_internal/processes/__init__.py
bbprep/_internal/processes/angle.py
bbprep/_internal/processes/ditopicfitter.py
bbprep/_internal/processes/planarfy.py
bbprep/_internal/processes/process.py
bbprep/_internal/processes/torsion.py
bbprep/_internal/selectors/__init__.py
bbprep/_internal/selectors/all_selector.py
bbprep/_internal/selectors/binders.py
bbprep/_internal/selectors/by_id.py
bbprep/_internal/selectors/by_smarts.py
bbprep/_internal/selectors/deleters.py
bbprep/_internal/selectors/notplacers.py
bbprep/_internal/selectors/selector.py
bbprep/_internal/selectors/xcomx.py
bbprepared-2025.12.8.1.dist-info/licenses/LICENSE
bbprepared-2025.12.8.1.dist-info/METADATA
bbprepared-2025.12.8.1.dist-info/WHEEL
bbprepared-2025.12.8.1.dist-info/top_level.txt
bbprepared-2025.12.8.1.dist-info/RECORD
