Metadata-Version: 2.4
Name: bbprepared
Version: 2025.12.8.1
Maintainer-email: Andrew Tarzia <andrew.tarzia@gmail.com>
Project-URL: github, https://github.com/andrewtarzia/bbprepared
Project-URL: documentation, https://bbprepared.readthedocs.io
Requires-Python: >=3.11
License-File: LICENSE
Requires-Dist: rdkit
Requires-Dist: stk
Requires-Dist: stko
Provides-Extra: dev
Requires-Dist: ruff; extra == "dev"
Requires-Dist: mypy; extra == "dev"
Requires-Dist: pip-tools; extra == "dev"
Requires-Dist: pytest<8; extra == "dev"
Requires-Dist: pytest-benchmark; extra == "dev"
Requires-Dist: pytest-datadir; extra == "dev"
Requires-Dist: pytest-lazy-fixture; extra == "dev"
Requires-Dist: pytest-cov; extra == "dev"
Requires-Dist: twine; extra == "dev"
Requires-Dist: sphinx; extra == "dev"
Requires-Dist: sphinx-copybutton; extra == "dev"
Requires-Dist: build; extra == "dev"
Requires-Dist: furo; extra == "dev"
Requires-Dist: moldoc; extra == "dev"
Dynamic: license-file
